Metadata-Version: 1.1
Name: easy-stocks
Version: 0.0.0
Summary: making finance esayer for developpers
Home-page: UNKNOWN
Author: Adam Maras
Author-email: adam3.maras@gmail.com
License: MIT
Keywords: stockstocks
Platform: UNKNOWN
Classifier: Development Status :: 5 - Production/Stable
Classifier: Intended Audience :: Education
Classifier: Operating System :: Microsoft :: Windows :: Windows 10
Classifier: License :: OSI Approved :: MIT License
Classifier: Programming Language :: Python :: 3
